prettymapp/__init__.py
prettymapp/geo.py
prettymapp/osm.py
prettymapp/plotting.py
prettymapp/settings.py
prettymapp/fonts/PermanentMarker-Regular.ttf
prettymapp/tests/__init__.py
prettymapp/tests/test_geo.py
prettymapp/tests/test_main.py
prettymapp/tests/test_osm.py
prettymapp/tests/test_plotting.py
prettymapp-0.6.0.dist-info/METADATA
prettymapp-0.6.0.dist-info/WHEEL
prettymapp-0.6.0.dist-info/top_level.txt
prettymapp-0.6.0.dist-info/RECORD
