Metadata-Version: 2.4
Name: prettymapp
Version: 0.6.0
Summary: Create beautiful maps from OpenStreetMap data
Author-email: Christoph Rieke <christoph.k.rieke@gmail.com>
License: MIT
Project-URL: Homepage, https://github.com/chrieke/prettymapp
Project-URL: Changelog, https://github.com/chrieke/prettymapp/changelog
Keywords: art,map,cartography,osm,streamlit
Classifier: Programming Language :: Python :: 3
Classifier: License :: OSI Approved :: MIT License
Classifier: Operating System :: OS Independent
Classifier: Development Status :: 4 - Beta
Classifier: Intended Audience :: Developers
Requires-Python: >=3.11
Requires-Dist: matplotlib>=3.10.8
Requires-Dist: osmnx>=2.0.7
Requires-Dist: pandas>=2.3.3
Provides-Extra: streamlit
Requires-Dist: streamlit; extra == "streamlit"
Requires-Dist: streamlit-image-select; extra == "streamlit"
